nonebot_plugin_broadcast/__init__.py
nonebot_plugin_broadcast-0.1.1.dist-info/WHEEL
nonebot_plugin_broadcast-0.1.1.dist-info/METADATA
nonebot_plugin_broadcast-0.1.1.dist-info/licenses/LICENSE
nonebot_plugin_broadcast-0.1.1.dist-info/RECORD
