Metadata-Version: 2.1
Name: nonebot-plugin-broadcast
Version: 0.1.1
Summary: NoneBot2 plugin for broadcast
License: MIT
Author-email: Akirami <Akiramiaya@outlook.com>
Requires-Python: >=3.8
Requires-Dist: nonebot-adapter-onebot>=2.1.5
Requires-Dist: nonebot2>=2.0.0rc2
Project-URL: Homepage, https://github.com/A-kirami/nonebot-plugin-broadcast
Project-URL: Repository, https://github.com/A-kirami/nonebot-plugin-broadcast
